mem_sram.v
module mem_sram (
    input clk,
    input [3:0] A,
    input WRITE,
    input READ,
    input [3:0] Din,
    output reg [3:0] Dout
);
    reg [3:0] mem [0:15];

    // Write data
    always @(posedge clk) begin
        if (WRITE) mem[A] <= Din;
    end

    // Read data
    always @(posedge clk) begin
        if (READ) Dout <= mem[A];
        else Dout <= 4'b0;
    end
endmodule

mem_async.v
module mem_async (
    input [3:0] A,
    input WRITE,
    input READ,
    input [3:0] Din,
    output [3:0] Dout
);
    reg [3:0] mem [0:15];

    // Write data
    always @(*) begin
        if (WRITE) mem[A] = Din;
    end

    // Read data
    assign Dout = READ ? mem[A] : 4'b0;
endmodule

tb_mem.sv
module tb_mem;
    reg clk;
    reg [3:0] A;
    reg WRITE;
    reg READ;
    reg [3:0] Din;
    
    wire [3:0] Dout_async;
    wire [3:0] Dout_sram;

    int errors = 0;

    // Async mem
    mem_async u_async (
        .A(A),
        .WRITE(WRITE),
        .READ(READ),
        .Din(Din),
        .Dout(Dout_async)
    );

    // Sync mem
    mem_sram u_sram (
        .clk(clk),
        .A(A),
        .WRITE(WRITE),
        .READ(READ),
        .Din(Din),
        .Dout(Dout_sram)
    );

    // Clock gen
    initial begin
        clk = 0;
        forever #5 clk = ~clk;
    end

    // Test flow
    initial begin
        $dumpfile("tb_mem.vcd");
        $dumpvars(0, tb_mem);

        // Init sigs
        A = 0;
        WRITE = 0;
        READ = 0;
        Din = 0;

        @(negedge clk);
        
        $display("--- Starting Memory Test ---");
        
        // 1. Write to all addresses
        $display("Test 1: Write all addresses");
        for (int i = 0; i < 16; i++) begin
            A = i;
            Din = ~i[3:0]; // Data pattern = inverted address
            WRITE = 1;
            @(negedge clk);
        end
        WRITE = 0;
        @(negedge clk);

        // 2. Read back and verify all addresses
        $display("Test 2: Read and verify all addresses");
        for (int i = 0; i < 16; i++) begin
            A = i;
            READ = 1;
            @(negedge clk); // Give clock edge for SRAM output
            if (Dout_async !== ~i[3:0]) begin
                $display("ERROR (Async): Addr %0d Expected %h Got %h", i, ~i[3:0], Dout_async);
                errors++;
            end
            if (Dout_sram !== ~i[3:0]) begin
                $display("ERROR (SRAM): Addr %0d Expected %h Got %h", i, ~i[3:0], Dout_sram);
                errors++;
            end
        end
        READ = 0;
        @(negedge clk);

        // 3. Test output when READ is deactivated
        $display("Test 3: Output behavior when READ=0");
        A = 5;
        READ = 0;
        @(negedge clk); // Give clock edge for SRAM output to clear
        if (Dout_async !== 4'b0) begin
            $display("ERROR (Async): Output not zero when READ=0. Got %h", Dout_async);
            errors++;
        end
        if (Dout_sram !== 4'b0) begin
            $display("ERROR (SRAM): Output not zero when READ=0. Got %h", Dout_sram);
            errors++;
        end

        // 4. Simultaneous Write and Read
        $display("Test 4: Simultaneous Read-During-Write");
        // We know from Test 1 that mem[10] (4'hA) holds 4'h5 (~4'hA)
        A = 4'hA;
        Din = 4'h3;
        WRITE = 1;
        READ = 1;
        @(negedge clk); // We just passed a posedge clock. SRAM wrote 3, SRAM read latched old data (5).
        
        // Asynchronous design should combinatorially show new data '3'
        if (Dout_async !== 4'h3) begin
            $display("ERROR (Async): Read-during-write failed. Expected 3, got %h", Dout_async);
            errors++;
        end
        // Synchronous design captures the old data '5'
        if (Dout_sram !== 4'h5) begin
            $display("ERROR (SRAM): Read-during-write failed. Expected old data 5, got %h", Dout_sram);
            errors++;
        end

        // Wait another clock cycle — now SRAM read output should reflect newly written data '3'
        @(negedge clk);
        if (Dout_sram !== 4'h3) begin
            $display("ERROR (SRAM): Post read-during-write output update failed. Expected 3, got %h", Dout_sram);
            errors++;
        end

        WRITE = 0;
        READ = 0;
        @(negedge clk);
        
        $display("--- Test Summary ---");
        if (errors == 0)
            $display("PASSED: 0 errors");
        else
            $display("FAILED: %0d errors", errors);
        
        $finish;
    end
endmodule

tb_mem.vcd
$date
	Tue Mar 31 17:50:03 2026
$end
$version
	Icarus Verilog
$end
$timescale
	1s
$end
$scope module tb_mem $end
$var wire 4 ! Dout_sram [3:0] $end
$var wire 4 " Dout_async [3:0] $end
$var reg 4 # A [3:0] $end
$var reg 4 $ Din [3:0] $end
$var reg 1 % READ $end
$var reg 1 & WRITE $end
$var reg 1 ' clk $end
$var integer 32 ( errors [31:0] $end
$scope module u_async $end
$var wire 4 ) A [3:0] $end
$var wire 4 * Din [3:0] $end
$var wire 1 % READ $end
$var wire 1 & WRITE $end
$var wire 4 + Dout [3:0] $end
$upscope $end
$scope module u_sram $end
$var wire 4 , A [3:0] $end
$var wire 4 - Din [3:0] $end
$var wire 1 % READ $end
$var wire 1 & WRITE $end
$var wire 1 ' clk $end
$var reg 4 . Dout [3:0] $end
$upscope $end
$scope begin $ivl_for_loop0 $end
$var integer 32 / i [31:0] $end
$upscope $end
$scope begin $ivl_for_loop1 $end
$var integer 32 0 i [31:0] $end
$upscope $end
$upscope $end
$enddefinitions $end
$comment Show the parameter values. $end
$dumpall
$end
#0
$dumpvars
b0 0
b0 /
bx .
b0 -
b0 ,
b0 +
b0 *
b0 )
b0 (
0'
0&
0%
b0 $
b0 #
b0 "
bx !
$end
#5
b0 !
b0 .
1'
#10
1&
b1111 $
b1111 *
b1111 -
0'
#15
1'
#20
b1110 $
b1110 *
b1110 -
b1 #
b1 )
b1 ,
b1 /
0'
#25
1'
#30
b1101 $
b1101 *
b1101 -
b10 #
b10 )
b10 ,
b10 /
0'
#35
1'
#40
b1100 $
b1100 *
b1100 -
b11 #
b11 )
b11 ,
b11 /
0'
#45
1'
#50
b1011 $
b1011 *
b1011 -
b100 #
b100 )
b100 ,
b100 /
0'
#55
1'
#60
b1010 $
b1010 *
b1010 -
b101 #
b101 )
b101 ,
b101 /
0'
#65
1'
#70
b1001 $
b1001 *
b1001 -
b110 #
b110 )
b110 ,
b110 /
0'
#75
1'
#80
b1000 $
b1000 *
b1000 -
b111 #
b111 )
b111 ,
b111 /
0'
#85
1'
#90
b111 $
b111 *
b111 -
b1000 #
b1000 )
b1000 ,
b1000 /
0'
#95
1'
#100
b110 $
b110 *
b110 -
b1001 #
b1001 )
b1001 ,
b1001 /
0'
#105
1'
#110
b101 $
b101 *
b101 -
b1010 #
b1010 )
b1010 ,
b1010 /
0'
#115
1'
#120
b100 $
b100 *
b100 -
b1011 #
b1011 )
b1011 ,
b1011 /
0'
#125
1'
#130
b11 $
b11 *
b11 -
b1100 #
b1100 )
b1100 ,
b1100 /
0'
#135
1'
#140
b10 $
b10 *
b10 -
b1101 #
b1101 )
b1101 ,
b1101 /
0'
#145
1'
#150
b1 $
b1 *
b1 -
b1110 #
b1110 )
b1110 ,
b1110 /
0'
#155
1'
#160
b0 $
b0 *
b0 -
b1111 #
b1111 )
b1111 ,
b1111 /
0'
#165
1'
#170
0&
b10000 /
0'
#175
1'
#180
b1111 "
b1111 +
1%
b0 #
b0 )
b0 ,
0'
#185
b1111 !
b1111 .
1'
#190
b1110 "
b1110 +
b1 #
b1 )
b1 ,
b1 0
0'
#195
b1110 !
b1110 .
1'
#200
b1101 "
b1101 +
b10 #
b10 )
b10 ,
b10 0
0'
#205
b1101 !
b1101 .
1'
#210
b1100 "
b1100 +
b11 #
b11 )
b11 ,
b11 0
0'
#215
b1100 !
b1100 .
1'
#220
b1011 "
b1011 +
b100 #
b100 )
b100 ,
b100 0
0'
#225
b1011 !
b1011 .
1'
#230
b1010 "
b1010 +
b101 #
b101 )
b101 ,
b101 0
0'
#235
b1010 !
b1010 .
1'
#240
b1001 "
b1001 +
b110 #
b110 )
b110 ,
b110 0
0'
#245
b1001 !
b1001 .
1'
#250
b1000 "
b1000 +
b111 #
b111 )
b111 ,
b111 0
0'
#255
b1000 !
b1000 .
1'
#260
b111 "
b111 +
b1000 #
b1000 )
b1000 ,
b1000 0
0'
#265
b111 !
b111 .
1'
#270
b110 "
b110 +
b1001 #
b1001 )
b1001 ,
b1001 0
0'
#275
b110 !
b110 .
1'
#280
b101 "
b101 +
b1010 #
b1010 )
b1010 ,
b1010 0
0'
#285
b101 !
b101 .
1'
#290
b100 "
b100 +
b1011 #
b1011 )
b1011 ,
b1011 0
0'
#295
b100 !
b100 .
1'
#300
b11 "
b11 +
b1100 #
b1100 )
b1100 ,
b1100 0
0'
#305
b11 !
b11 .
1'
#310
b10 "
b10 +
b1101 #
b1101 )
b1101 ,
b1101 0
0'
#315
b10 !
b10 .
1'
#320
b1 "
b1 +
b1110 #
b1110 )
b1110 ,
b1110 0
0'
#325
b1 !
b1 .
1'
#330
b0 "
b0 +
b1111 #
b1111 )
b1111 ,
b1111 0
0'
#335
b0 !
b0 .
1'
#340
0%
b10000 0
0'
#345
1'
#350
b101 #
b101 )
b101 ,
0'
#355
1'
#360
b11 "
b11 +
1%
1&
b11 $
b11 *
b11 -
b1010 #
b1010 )
b1010 ,
0'
#365
b101 !
b101 .
1'
#370
0'
#375
b11 !
b11 .
1'
#380
b0 "
b0 +
0%
0&
0'
#385
b0 !
b0 .
1'
